pyorderby/__init__.py
pyorderby/sorter.py
pyorderby/tests/__init__.py
pyorderby/tests/test_api.py
pyorderby/tests/test_sorter.py
pyorderby-1.0.0.dist-info/DESCRIPTION.rst
pyorderby-1.0.0.dist-info/METADATA
pyorderby-1.0.0.dist-info/RECORD
pyorderby-1.0.0.dist-info/WHEEL
pyorderby-1.0.0.dist-info/metadata.json
pyorderby-1.0.0.dist-info/top_level.txt
tests/__init__.py
